{"cameraMode":{"drawMode":0,"name":"Shaded","section":"Shading Mode"},"sceneLighting":true,"audioPlay":false,"sceneViewState":{"m_AlwaysRefresh":false,"showFog":true,"showSkybox":true,"showFlares":true,"showImageEffects":true,"showParticleSystems":true,"showVisualEffectGraphs":true,"m_FxEnabled":true},"in2DMode":false,"pivot":{"x":10.808688163757325,"y":5.123377799987793,"z":5.09492826461792},"rotation":{"x":0.057363323867321017,"y":-0.6747368574142456,"z":0.052736420184373859,"w":0.7339354753494263},"size":0.8660253882408142,"orthographic":false}